pymusix/__init__.py
pymusix/pymusix.py
pymusix-1.0.0.dist-info/LICENSE
pymusix-1.0.0.dist-info/METADATA
pymusix-1.0.0.dist-info/WHEEL
pymusix-1.0.0.dist-info/top_level.txt
pymusix-1.0.0.dist-info/RECORD
