Metadata-Version: 2.1
Name: pymusix
Version: 1.0.0
Summary: 🌿 Retrieve information about a song, including details like the artist, album, release date, genres, and lyrics using Spotify and MusixMatch API
Home-page: https://github.com/TrueMyst/pymusix
Author: TrueMyst
License: MIT
Classifier: Development Status :: 4 - Beta
Classifier: Intended Audience :: Developers
Classifier: License :: OSI Approved :: MIT License
Classifier: Programming Language :: Python :: 3.8
Classifier: Programming Language :: Python :: 3.9
Classifier: Topic :: Internet
Classifier: Topic :: Software Development :: Libraries
Classifier: Topic :: Software Development :: Libraries :: Python Modules
Classifier: Topic :: Utilities
Requires-Python: >=3.8
License-File: LICENSE
